abacura_kallisti/__init__.py
abacura_kallisti/case.py
abacura_kallisti/context.py
abacura_kallisti/screens.py
abacura_kallisti/atlas/__init__.py
abacura_kallisti/atlas/bfs.py
abacura_kallisti/atlas/encounter.py
abacura_kallisti/atlas/item.py
abacura_kallisti/atlas/location.py
abacura_kallisti/atlas/messages.py
abacura_kallisti/atlas/navigator.py
abacura_kallisti/atlas/room.py
abacura_kallisti/atlas/terrain.py
abacura_kallisti/atlas/tour_guide.py
abacura_kallisti/atlas/travel_guide.py
abacura_kallisti/atlas/wilderness.py
abacura_kallisti/atlas/wilderness_map.py
abacura_kallisti/atlas/world.py
abacura_kallisti/css/kallisti.css
abacura_kallisti/metrics/__init__.py
abacura_kallisti/metrics/odometer.py
abacura_kallisti/mud/__init__.py
abacura_kallisti/mud/affect.py
abacura_kallisti/mud/area.py
abacura_kallisti/mud/experience.py
abacura_kallisti/mud/group.py
abacura_kallisti/mud/mob.py
abacura_kallisti/mud/msdp.py
abacura_kallisti/mud/player.py
abacura_kallisti/mud/skills.py
abacura_kallisti/mud/tasks.py
abacura_kallisti/plugins/__init__.py
abacura_kallisti/plugins/autobuf.py
abacura_kallisti/plugins/corpse.py
abacura_kallisti/plugins/lok.py
abacura_kallisti/plugins/lokcomms.py
abacura_kallisti/plugins/navigate.py
abacura_kallisti/plugins/queue.py
abacura_kallisti/plugins/atlas/AreaController.py
abacura_kallisti/plugins/atlas/WorldController.py
abacura_kallisti/plugins/atlas/__init__.py
abacura_kallisti/plugins/atlas/atlas_helper.py
abacura_kallisti/plugins/atlas/big_map.py
abacura_kallisti/plugins/atlas/location_controller.py
abacura_kallisti/plugins/atlas/room_watcher.py
abacura_kallisti/plugins/atlas/travel_helper.py
abacura_kallisti/plugins/msdp/__init__.py
abacura_kallisti/plugins/msdp/msdp.py
abacura_kallisti/plugins/msdp/msdp_controller.py
abacura_kallisti/plugins/odometer/__init__.py
abacura_kallisti/plugins/odometer/odometer.py
abacura_kallisti/plugins/scripts/__init__.py
abacura_kallisti/plugins/scripts/tour_demo.py
abacura_kallisti/plugins/scripts/travel.py
abacura_kallisti-0.0.8.dist-info/METADATA
abacura_kallisti-0.0.8.dist-info/WHEEL
abacura_kallisti-0.0.8.dist-info/top_level.txt
abacura_kallisti-0.0.8.dist-info/RECORD
