Metadata-Version: 2.1
Name: abacura_kallisti
Version: 0.0.8
Summary: Abacura extensions for Legends of Kallisti
License: Proprietary
Classifier: License :: Other/Proprietary License
Requires-Python: >3.10
Requires-Dist: abacura ~=0.0.15
Requires-Dist: pillow
